dashcorn/__init__.py
dashcorn-0.0.4.dist-info/METADATA
dashcorn-0.0.4.dist-info/WHEEL
dashcorn-0.0.4.dist-info/top_level.txt
dashcorn-0.0.4.dist-info/RECORD
